scivianna/VERSION
scivianna/__init__.py
scivianna/constants.py
scivianna/enums.py
scivianna/notebook_tools.py
scivianna/readme.md
scivianna/slave.py
scivianna/agent/__init__.py
scivianna/agent/data_2d_worker.py
scivianna/agent/instructions.md
scivianna/agent/llm_model.py
scivianna/component/__init__.py
scivianna/component/gridstack_component.py
scivianna/component/overlay_component.py
scivianna/component/server_file_browser.py
scivianna/component/splitjs_component.py
scivianna/coupling/__init__.py
scivianna/coupling/icoco.py
scivianna/data/__init__.py
scivianna/data/data1d.py
scivianna/data/data2d.py
scivianna/data/data_2d_worker.py
scivianna/data/data_container.py
scivianna/extension/__init__.py
scivianna/extension/ai_assistant.py
scivianna/extension/axes.py
scivianna/extension/coupling.py
scivianna/extension/extension.py
scivianna/extension/field_selector.py
scivianna/extension/file_loader.py
scivianna/extension/layout.py
scivianna/extension/line_selector.py
scivianna/extension/save_load_extension.py
scivianna/icon/__init__.py
scivianna/icon/salome.svg
scivianna/input_file/__init__.py
scivianna/input_file/power.med
scivianna/interface/__init__.py
scivianna/interface/csv_result.py
scivianna/interface/generic_interface.py
scivianna/interface/med_interface.py
scivianna/interface/option_element.py
scivianna/interface/structured_mesh_interface.py
scivianna/interface/time_dataframe.py
scivianna/layout/__init__.py
scivianna/layout/generic_layout.py
scivianna/layout/gridstack.py
scivianna/layout/split.py
scivianna/panel/__init__.py
scivianna/panel/demo.py
scivianna/panel/gui.py
scivianna/panel/panel_1d.py
scivianna/panel/panel_2d.py
scivianna/panel/visualisation_panel.py
scivianna/plotter_1d/__init__.py
scivianna/plotter_1d/bokeh_1d_plotter.py
scivianna/plotter_1d/generic_plotter.py
scivianna/plotter_2d/__init__.py
scivianna/plotter_2d/api.py
scivianna/plotter_2d/generic_plotter.py
scivianna/plotter_2d/grid/__init__.py
scivianna/plotter_2d/grid/bokeh.py
scivianna-0.3.3.dist-info/METADATA
scivianna-0.3.3.dist-info/WHEEL
scivianna-0.3.3.dist-info/top_level.txt
scivianna-0.3.3.dist-info/RECORD
