Metadata-Version: 2.4
Name: scivianna
Version: 0.3.3
Summary: Python generic module to visualize simulation geometries and results.
Author: CEA
Author-email: Thibault.Moulignier@cea.fr
Maintainer: Thibault Moulignier
Keywords: visualization
Requires-Python: >=3.8, <4
Requires-Dist: panel
Requires-Dist: rasterio
Requires-Dist: matplotlib
Requires-Dist: numpy
Requires-Dist: shapely
Requires-Dist: jupyter_bokeh
Requires-Dist: holoviews
Requires-Dist: icoco~=2.0.0
Requires-Dist: panel_material_ui
Requires-Dist: geopandas
Requires-Dist: dill
Provides-Extra: default
Provides-Extra: agent
Requires-Dist: smolagents[openai]; extra == "agent"
Provides-Extra: pyvista
Requires-Dist: pyvista; extra == "pyvista"
Dynamic: author
Dynamic: author-email
Dynamic: description
Dynamic: keywords
Dynamic: maintainer
Dynamic: provides-extra
Dynamic: requires-dist
Dynamic: requires-python
Dynamic: summary
